BootstrapXiaoShu/README.md
BootstrapXiaoShu/__init__.py
BootstrapXiaoShu/__main__.py
BootstrapXiaoShu/file.epub
BootstrapXiaoShu/index.html
BootstrapXiaoShu/css/__init__.py
BootstrapXiaoShu/css/annotations.css
BootstrapXiaoShu/css/main.css
BootstrapXiaoShu/css/normalize.css
BootstrapXiaoShu/css/popup.css
BootstrapXiaoShu/font/__init__.py
BootstrapXiaoShu/font/fontello.eot
BootstrapXiaoShu/font/fontello.svg
BootstrapXiaoShu/font/fontello.ttf
BootstrapXiaoShu/font/fontello.woff
BootstrapXiaoShu/img/__init__.py
BootstrapXiaoShu/img/annotator-glyph-sprite.png
BootstrapXiaoShu/img/annotator-icon-sprite.png
BootstrapXiaoShu/img/apple-touch-icon.png
BootstrapXiaoShu/img/cancelfullscreen.png
BootstrapXiaoShu/img/close.png
BootstrapXiaoShu/img/fullscreen.png
BootstrapXiaoShu/img/loader.gif
BootstrapXiaoShu/img/menu-icon.png
BootstrapXiaoShu/img/save.png
BootstrapXiaoShu/img/saved.png
BootstrapXiaoShu/img/settings-s.png
BootstrapXiaoShu/img/settings.png
BootstrapXiaoShu/img/star.png
BootstrapXiaoShu/js/__init__.py
BootstrapXiaoShu/js/epub.js
BootstrapXiaoShu/js/epub.min.js
BootstrapXiaoShu/js/epub.min.map
BootstrapXiaoShu/js/hooks.min.js
BootstrapXiaoShu/js/hooks.min.map
BootstrapXiaoShu/js/reader.js
BootstrapXiaoShu/js/reader.js.map
BootstrapXiaoShu/js/reader.min.js
BootstrapXiaoShu/js/reader.min.map
BootstrapXiaoShu/js/hooks/__init__.py
BootstrapXiaoShu/js/hooks/extensions/__init__.py
BootstrapXiaoShu/js/hooks/extensions/highlight.js
BootstrapXiaoShu/js/libs/__init__.py
BootstrapXiaoShu/js/libs/jquery.min.js
BootstrapXiaoShu/js/libs/localforage.min.js
BootstrapXiaoShu/js/libs/screenfull.js
BootstrapXiaoShu/js/libs/screenfull.min.js
BootstrapXiaoShu/js/libs/zip.min.js
BootstrapXiaoShu/js/plugins/__init__.py
BootstrapXiaoShu/js/plugins/hypothesis.js
BootstrapXiaoShu/js/plugins/search.js
bootstrap_xiao_shu-2024.3.1.0.dist-info/METADATA
bootstrap_xiao_shu-2024.3.1.0.dist-info/WHEEL
bootstrap_xiao_shu-2024.3.1.0.dist-info/entry_points.txt
bootstrap_xiao_shu-2024.3.1.0.dist-info/top_level.txt
bootstrap_xiao_shu-2024.3.1.0.dist-info/RECORD
